odoo/addons/partner_deduplicate_filter/README.rst
odoo/addons/partner_deduplicate_filter/__init__.py
odoo/addons/partner_deduplicate_filter/__manifest__.py
odoo/addons/partner_deduplicate_filter/i18n/crm_deduplicate_filter.pot
odoo/addons/partner_deduplicate_filter/i18n/de.po
odoo/addons/partner_deduplicate_filter/i18n/es.po
odoo/addons/partner_deduplicate_filter/i18n/hr.po
odoo/addons/partner_deduplicate_filter/i18n/it.po
odoo/addons/partner_deduplicate_filter/i18n/nl_NL.po
odoo/addons/partner_deduplicate_filter/i18n/partner_deduplicate_filter.pot
odoo/addons/partner_deduplicate_filter/i18n/sk.po
odoo/addons/partner_deduplicate_filter/i18n/sl.po
odoo/addons/partner_deduplicate_filter/i18n/tr.po
odoo/addons/partner_deduplicate_filter/readme/CONTRIBUTORS.md
odoo/addons/partner_deduplicate_filter/readme/DESCRIPTION.md
odoo/addons/partner_deduplicate_filter/readme/USAGE.md
odoo/addons/partner_deduplicate_filter/static/description/icon.png
odoo/addons/partner_deduplicate_filter/static/description/icon.svg
odoo/addons/partner_deduplicate_filter/static/description/index.html
odoo/addons/partner_deduplicate_filter/tests/__init__.py
odoo/addons/partner_deduplicate_filter/tests/test_partner_deduplicate_filter.py
odoo/addons/partner_deduplicate_filter/wizards/__init__.py
odoo/addons/partner_deduplicate_filter/wizards/partner_merge.py
odoo/addons/partner_deduplicate_filter/wizards/partner_merge_view.xml
odoo_addon_partner_deduplicate_filter-18.0.1.0.0.2.dist-info/METADATA
odoo_addon_partner_deduplicate_filter-18.0.1.0.0.2.dist-info/WHEEL
odoo_addon_partner_deduplicate_filter-18.0.1.0.0.2.dist-info/top_level.txt
odoo_addon_partner_deduplicate_filter-18.0.1.0.0.2.dist-info/RECORD
