Metadata-Version: 2.1
Name: odoo-addon-partner_deduplicate_filter
Version: 18.0.1.0.0.2
Requires-Python: >=3.10
Requires-Dist: odoo-addon-partner_deduplicate_acl==18.0.*
Requires-Dist: odoo==18.0.*
Summary: Exclude records from the deduplication
Home-page: https://github.com/OCA/partner-contact
License: AGPL-3
Author: Tecnativa, Odoo Community Association (OCA)
Author-email: support@odoo-community.org
Classifier: Programming Language :: Python
Classifier: Framework :: Odoo
Classifier: Framework :: Odoo :: 18.0
Classifier: License :: OSI Approved :: GNU Affero General Public License v3
